conan/__init__.py
conan/errors.py
conan/tools/__init__.py
conan/tools/_check_build_profile.py
conan/tools/_compilers.py
conan/tools/android/__init__.py
conan/tools/android/utils.py
conan/tools/apple/__init__.py
conan/tools/apple/apple.py
conan/tools/apple/xcodebuild.py
conan/tools/apple/xcodedeps.py
conan/tools/apple/xcodetoolchain.py
conan/tools/build/__init__.py
conan/tools/build/cppstd.py
conan/tools/build/cpu.py
conan/tools/build/cross_building.py
conan/tools/build/flags.py
conan/tools/build/stdcpp_library.py
conan/tools/cmake/__init__.py
conan/tools/cmake/cmake.py
conan/tools/cmake/file_api.py
conan/tools/cmake/layout.py
conan/tools/cmake/presets.py
conan/tools/cmake/utils.py
conan/tools/cmake/cmakedeps/__init__.py
conan/tools/cmake/cmakedeps/cmakedeps.py
conan/tools/cmake/cmakedeps/templates/__init__.py
conan/tools/cmake/cmakedeps/templates/config.py
conan/tools/cmake/cmakedeps/templates/config_version.py
conan/tools/cmake/cmakedeps/templates/macros.py
conan/tools/cmake/cmakedeps/templates/target_configuration.py
conan/tools/cmake/cmakedeps/templates/target_data.py
conan/tools/cmake/cmakedeps/templates/targets.py
conan/tools/cmake/toolchain/__init__.py
conan/tools/cmake/toolchain/blocks.py
conan/tools/cmake/toolchain/toolchain.py
conan/tools/env/__init__.py
conan/tools/env/environment.py
conan/tools/env/virtualbuildenv.py
conan/tools/env/virtualrunenv.py
conan/tools/files/__init__.py
conan/tools/files/conandata.py
conan/tools/files/copy_pattern.py
conan/tools/files/cpp_package.py
conan/tools/files/files.py
conan/tools/files/packager.py
conan/tools/files/patches.py
conan/tools/files/symlinks/__init__.py
conan/tools/files/symlinks/symlinks.py
conan/tools/gnu/__init__.py
conan/tools/gnu/autotools.py
conan/tools/gnu/autotoolsdeps.py
conan/tools/gnu/autotoolstoolchain.py
conan/tools/gnu/get_gnu_triplet.py
conan/tools/gnu/gnudeps_flags.py
conan/tools/gnu/pkgconfig.py
conan/tools/gnu/pkgconfigdeps.py
conan/tools/google/__init__.py
conan/tools/google/bazel.py
conan_zbuild-1.66.3.dist-info/METADATA
conan_zbuild-1.66.3.dist-info/WHEEL
conan_zbuild-1.66.3.dist-info/entry_points.txt
conan_zbuild-1.66.3.dist-info/top_level.txt
conan_zbuild-1.66.3.dist-info/RECORD
