Metadata-Version: 2.4
Name: conan-zbuild
Version: 1.66.3
Summary: Conan C/C++ package manager
Home-page: https://conan.io
Author: JFrog LTD
Author-email: luism@jfrog.com
License: MIT
Project-URL: Documentation, https://docs.conan.io
Project-URL: Source, https://github.com/conan-io/conan
Project-URL: Tracker, https://github.com/conan-io/conan/issues
Keywords: C/C++,package,libraries,developer,manager,dependency,tool,c,c++,cpp
Classifier: Development Status :: 5 - Production/Stable
Classifier: Intended Audience :: Developers
Classifier: Topic :: Software Development :: Build Tools
Classifier: License :: OSI Approved :: MIT License
Classifier: Programming Language :: Python :: 3
Classifier: Programming Language :: Python :: 3.6
Classifier: Programming Language :: Python :: 3.7
Classifier: Programming Language :: Python :: 3.8
Requires-Python: >=3.6
Requires-Dist: requests<3.0.0,>=2.25
Requires-Dist: urllib3<=2.2.3,>=1.26.6
Requires-Dist: colorama<0.5.0,>=0.3.3
Requires-Dist: PyYAML<6.1,>=3.11
Requires-Dist: patch-ng<1.18,>=1.17.4
Requires-Dist: fasteners>=0.14.1
Requires-Dist: six<=1.20.0,>=1.10.0
Requires-Dist: node-semver==0.6.1
Requires-Dist: distro<=1.8.0,>=1.0.2; sys_platform == "linux" or sys_platform == "linux2"
Requires-Dist: pygments<3.0,>=2.0
Requires-Dist: tqdm<5,>=4.28.1
Requires-Dist: Jinja2<3.0.0,>=2.9; python_version <= "2.7"
Requires-Dist: MarkupSafe<=2.0.1; python_version <= "2.7"
Requires-Dist: Jinja2<4.0.0,>=3.0; python_version >= "3"
Requires-Dist: python-dateutil<3,>=2.7.0
Requires-Dist: configparser>=3.5; python_version <= "2.7"
Requires-Dist: bottle<0.13,>=0.12.8
Requires-Dist: pluginbase>=0.5
Requires-Dist: PyJWT<3.0.0,>=2.4.0
Provides-Extra: dev
Requires-Dist: pytest<7.0.0,>=6.1.1; python_version > "3.0" and extra == "dev"
Requires-Dist: pytest>=4.6.11; python_version < "3.0" and extra == "dev"
Requires-Dist: pytest-xdist; extra == "dev"
Requires-Dist: parameterized>=0.6.3; extra == "dev"
Requires-Dist: mock<1.4.0,>=1.3.0; extra == "dev"
Requires-Dist: WebTest<2.1.0,>=2.0.18; extra == "dev"
Requires-Dist: bottle; extra == "dev"
Provides-Extra: test
Requires-Dist: pytest<7.0.0,>=6.1.1; python_version > "3.0" and extra == "test"
Requires-Dist: pytest>=4.6.11; python_version < "3.0" and extra == "test"
Requires-Dist: pytest-xdist; extra == "test"
Requires-Dist: parameterized>=0.6.3; extra == "test"
Requires-Dist: mock<1.4.0,>=1.3.0; extra == "test"
Requires-Dist: WebTest<2.1.0,>=2.0.18; extra == "test"
Requires-Dist: bottle; extra == "test"
Dynamic: author
Dynamic: author-email
Dynamic: classifier
Dynamic: description
Dynamic: description-content-type
Dynamic: home-page
Dynamic: keywords
Dynamic: license
Dynamic: project-url
Dynamic: provides-extra
Dynamic: requires-dist
Dynamic: requires-python
Dynamic: summary
